hexformat/__init__.py
hexformat/base.py
hexformat/fillpattern.py
hexformat/hexdump.py
hexformat/intelhex.py
hexformat/multipartbuffer.py
hexformat/srecord.py
hexformat/tektronix.py
hexformat-0.4.0.dist-info/LICENSE.txt
hexformat-0.4.0.dist-info/METADATA
hexformat-0.4.0.dist-info/WHEEL
hexformat-0.4.0.dist-info/top_level.txt
hexformat-0.4.0.dist-info/RECORD
